parse_aria_control_file/__init__.py
parse_aria_control_file/__version__.py
parse_aria_control_file/aria2_parser.py
parse_aria_control_file-1.1.0.dist-info/METADATA
parse_aria_control_file-1.1.0.dist-info/WHEEL
parse_aria_control_file-1.1.0.dist-info/top_level.txt
parse_aria_control_file-1.1.0.dist-info/RECORD
