Metadata-Version: 2.1
Name: parse-aria-control-file
Version: 1.1.0
Summary: Parse the information out of aria2 control files.
Home-page: https://github.com/meese-enterprises/aria-control-file-parser
Classifier: Programming Language :: Python :: 3
Requires-Python: >=3.0.0
Requires-Dist: argparse
Requires-Dist: setuptools
Requires-Dist: wheel
